ansible_mongodb_store/__init__.py
ansible_mongodb_store/mongodb_store.py
ansible_mongodb_store-0.3.0.dist-info/LICENSE.txt
ansible_mongodb_store-0.3.0.dist-info/METADATA
ansible_mongodb_store-0.3.0.dist-info/WHEEL
ansible_mongodb_store-0.3.0.dist-info/top_level.txt
ansible_mongodb_store-0.3.0.dist-info/RECORD
